layouts/__init__.py
layouts/__main__.py
layouts/emitter.py
layouts-0.4.10.dist-info/LICENSE
layouts-0.4.10.dist-info/WHEEL
layouts-0.4.10.dist-info/METADATA
layouts-0.4.10.dist-info/RECORD
