Metadata-Version: 2.1
Name: layouts
Version: 0.4.10
Summary: Python API for HID-IO HID Layouts Repository
Home-page: https://github.com/hid-io/layouts-python
License: UNKNOWN
Author: Jacob Alexander
Author-email: haata@kiibohd.com
Requires-Python: >=3.5
Classifier: Intended Audience :: Developers
Classifier: License :: OSI Approved :: MIT License
Classifier: Programming Language :: Python :: 3
Classifier: Topic :: Software Development :: Libraries :: Python Modules
Requires-Dist: requests
Requires-Dist: PyGithub
Requires-Dist: GitPython
